firepoint.py
firepointgui.py
firepoint-1.0.0.dist-info/METADATA
firepoint-1.0.0.dist-info/WHEEL
firepoint-1.0.0.dist-info/entry_points.txt
firepoint-1.0.0.dist-info/RECORD
