Metadata-Version: 2.1
Name: firepoint
Version: 1.0.0
Summary: prepares your images for laser engraving
Home-page: https://github.com/fdev31/firepoint
License: GPL
Author: fdev31
Author-email: fdev31@gmail.com
Requires-Python: >=3.9
Classifier: License :: Other/Proprietary License
Classifier: Programming Language :: Python :: 3
Classifier: Programming Language :: Python :: 3.9
Classifier: Programming Language :: Python :: 3.10
Classifier: Programming Language :: Python :: 3.11
Requires-Dist: numpy (>=1.25.2,<2.0.0)
Requires-Dist: opencv-python (>=4.8.0.76,<5.0.0.0)
Requires-Dist: pillow (>=10.0.1,<11.0.0)
